printnanny_factory_rest_api/__init__.py
printnanny_factory_rest_api/api_client.py
printnanny_factory_rest_api/api_response.py
printnanny_factory_rest_api/configuration.py
printnanny_factory_rest_api/exceptions.py
printnanny_factory_rest_api/rest.py
printnanny_factory_rest_api/api/__init__.py
printnanny_factory_rest_api/api/auth_api.py
printnanny_factory_rest_api/api/printers_api.py
printnanny_factory_rest_api/api/reservations_api.py
printnanny_factory_rest_api/api/schema_api.py
printnanny_factory_rest_api/api/users_api.py
printnanny_factory_rest_api/api/workspaces_api.py
printnanny_factory_rest_api/models/__init__.py
printnanny_factory_rest_api/models/authorization_grant_type_enum.py
printnanny_factory_rest_api/models/callback_token_auth_request.py
printnanny_factory_rest_api/models/client_type_enum.py
printnanny_factory_rest_api/models/duet_printer_backend.py
printnanny_factory_rest_api/models/duet_printer_backend_request.py
printnanny_factory_rest_api/models/duet_printer_backend_status_enum.py
printnanny_factory_rest_api/models/email_auth_redirect.py
printnanny_factory_rest_api/models/email_auth_redirect_request.py
printnanny_factory_rest_api/models/error_detail.py
printnanny_factory_rest_api/models/grant_type_enum.py
printnanny_factory_rest_api/models/maintenance_job.py
printnanny_factory_rest_api/models/maintenance_job_all_of.py
printnanny_factory_rest_api/models/maintenance_job_request.py
printnanny_factory_rest_api/models/maintenance_job_request_all_of.py
printnanny_factory_rest_api/models/maintenance_job_typed.py
printnanny_factory_rest_api/models/maintenance_job_typed_all_of.py
printnanny_factory_rest_api/models/maintenance_job_typed_request.py
printnanny_factory_rest_api/models/oauth2_application.py
printnanny_factory_rest_api/models/oauth2_application_request.py
printnanny_factory_rest_api/models/oauth2_introspect.py
printnanny_factory_rest_api/models/oauth2_introspect_request.py
printnanny_factory_rest_api/models/oauth2_token.py
printnanny_factory_rest_api-0.1.0rc202308191701.dist-info/METADATA
printnanny_factory_rest_api-0.1.0rc202308191701.dist-info/WHEEL
printnanny_factory_rest_api-0.1.0rc202308191701.dist-info/top_level.txt
printnanny_factory_rest_api-0.1.0rc202308191701.dist-info/RECORD
