Metadata-Version: 2.1
Name: printnanny-factory-rest-api
Version: 0.1.0rc202308191701
Summary: PrintNanny Factory API Documentation
Home-page: UNKNOWN
Author: Leigh Johnson
Author-email: leigh@printnanny.ai
License: AGPLv3
Keywords: OpenAPI,OpenAPI-Generator,PrintNanny Factory API Documentation
Platform: UNKNOWN
Requires-Dist: aenum
Requires-Dist: aiohttp >=3.0.0
Requires-Dist: pydantic <2,>=1.10.5
Requires-Dist: python-dateutil
Requires-Dist: urllib3 >=1.25.3
